Metadata-Version: 2.1
Name: gb-alpha
Version: 3.0.0
Summary: Gameball Python SDK provides convinient access to the Gameball API frpm applications written in the Python langauage
Home-page: https://github.com/gameballers/gameball-python
Author: Gameball
Author-email: support@gameball.co
License: UNKNOWN
Platform: UNKNOWN
Requires-Python: >=3.4
License-File: LICENSE
